xyz_pack/__init__.py
xyz_pack/first_pack/__init__.py
xyz_pack/first_pack/addition.py
xyz_pack/first_pack/subtraction.py
xyz_pack/second_pack/__init__.py
xyz_pack/second_pack/division.py
xyz_pack/second_pack/multiplication.py
xyz_pack-0.1.dist-info/LICENCE.txt
xyz_pack-0.1.dist-info/METADATA
xyz_pack-0.1.dist-info/WHEEL
xyz_pack-0.1.dist-info/top_level.txt
xyz_pack-0.1.dist-info/RECORD
