Metadata-Version: 2.1
Name: xyz-pack
Version: 0.1
Summary: This is simple package
Home-page: UNKNOWN
Author: kishorkumarmohanraj
Author-email: kishorkumar.mohanraj@hexacorp.com
License: UNKNOWN
Platform: UNKNOWN
Classifier: Programming Language :: Python :: 3
Classifier: License :: OSI Approved :: MIT License
Classifier: Operating System :: OS Independent
License-File: LICENCE.txt
